myPackage/__init__.py
myPackage/myModule.py
myExamplePackage-0.0.2.dist-info/METADATA
myExamplePackage-0.0.2.dist-info/WHEEL
myExamplePackage-0.0.2.dist-info/top_level.txt
myExamplePackage-0.0.2.dist-info/RECORD
