Metadata-Version: 2.1
Name: myExamplePackage
Version: 0.0.2
Summary: this is a test package
Home-page: UNKNOWN
Author: Arpit Rathi
Author-email: arpit97rathi@gmail.com
License: UNKNOWN
Platform: UNKNOWN
